setup.py
pynetmodule/__init__.py
pynetmodule.egg-info/PKG-INFO
pynetmodule.egg-info/SOURCES.txt
pynetmodule.egg-info/dependency_links.txt
pynetmodule.egg-info/top_level.txt