Metadata-Version: 1.0
Name: pynetmodule
Version: 1.0
Summary:  ---- PYNETMODULE ----
Home-page: UNKNOWN
Author: UNKNOWN
Author-email: kislukdanila@gmail.com
License: UNKNOWN
Platform: UNKNOWN
